stime/__init__.py
stime/stime.py
stime/test_stime.py
stime-1.0.0.dist-info/LICENSE
stime-1.0.0.dist-info/METADATA
stime-1.0.0.dist-info/WHEEL
stime-1.0.0.dist-info/top_level.txt
stime-1.0.0.dist-info/RECORD
