Metadata-Version: 2.1
Name: stime
Version: 1.0.0
Summary: A testing (and partial) replacement for the time package, for fully-controlled time-dependent tests.
Home-page: https://github.com/gonzalo-bulnes/stime
Author: Gonzalo Bulnes Guilpain
Author-email: gon.bulnes@fastmail.com
License: UNKNOWN
Platform: UNKNOWN
Classifier: Programming Language :: Python :: 3
Classifier: License :: OSI Approved :: GNU General Public License v3 or later (GPLv3+)
Classifier: Operating System :: OS Independent
